quantilecoint/__init__.py
quantilecoint/core/__init__.py
quantilecoint/core/augmented.py
quantilecoint/core/fully_modified.py
quantilecoint/core/quantile_cointegration.py
quantilecoint/core/quantile_regression.py
quantilecoint/output/__init__.py
quantilecoint/output/formatter.py
quantilecoint/simulation/__init__.py
quantilecoint/simulation/bootstrap.py
quantilecoint/simulation/critical_values.py
quantilecoint/tests_stats/__init__.py
quantilecoint/tests_stats/cointegration_test.py
quantilecoint/tests_stats/stability_test.py
quantilecoint/tests_stats/wald_test.py
quantilecoint/utils/__init__.py
quantilecoint/utils/kernels.py
quantilecoint/utils/long_run_variance.py
quantilecoint/utils/sparsity.py
quantilecoint-1.0.1.dist-info/licenses/LICENSE
quantilecoint-1.0.1.dist-info/METADATA
quantilecoint-1.0.1.dist-info/WHEEL
quantilecoint-1.0.1.dist-info/top_level.txt
quantilecoint-1.0.1.dist-info/RECORD
